CHANGELOG.txt
MANIFEST.in
README.rst
setup.cfg
setup.py
pyfasta/__init__.py
pyfasta/fasta.py
pyfasta/records.py
pyfasta/split_fasta.py
pyfasta.egg-info/PKG-INFO
pyfasta.egg-info/SOURCES.txt
pyfasta.egg-info/dependency_links.txt
pyfasta.egg-info/entry_points.txt
pyfasta.egg-info/not-zip-safe
pyfasta.egg-info/top_level.txt
tests/bench.py
tests/test_all.py
tests/data/key.fasta
tests/data/three_chrs.fasta