Metadata-Version: 1.0
Name: pyfasta
Version: 0.4.0
Summary: fast, memory-efficient, pythonic (and command-line) access to fasta sequence files
Home-page: http://github.com/brentp/pyfasta/
Author: brentp
Author-email: bpederse@gmail.com
License: MIT
Keywords: bioinformatics blast fasta
Platform: UNKNOWN
Classifier: Topic :: Scientific/Engineering :: Bio-Informatics
